<annotation>
	<folder>images</folder>
	<filename>1B2UESP0.jpg</filename>
	<path>/Users/saibasak/Workspace/hands-on-ai-with-tensorflow/section_2/03_object_detection_yolov2/data/images/1B2UESP0.jpg</path>
	<source>
		<database>Unknown</database>
	</source>
	<size>
		<width>233</width>
		<height>216</height>
		<depth>3</depth>
	</size>
	<segmented>0</segmented>
	<object>
		<name>stop_sign</name>
		<pose>Unspecified</pose>
		<truncated>0</truncated>
		<difficult>0</difficult>
		<bndbox>
			<xmin>105</xmin>
			<ymin>17</ymin>
			<xmax>155</xmax>
			<ymax>66</ymax>
		</bndbox>
	</object>
</annotation>
